MANIFEST.in
README.md
pyproject.toml
setup.py
amuse_huayno.egg-info/PKG-INFO
amuse_huayno.egg-info/SOURCES.txt
amuse_huayno.egg-info/dependency_links.txt
amuse_huayno.egg-info/requires.txt
amuse_huayno.egg-info/top_level.txt
src/amuse/community/huayno/Makefile
src/amuse/community/huayno/__init__.py
src/amuse/community/huayno/_version.py
src/amuse/community/huayno/interface.c
src/amuse/community/huayno/interface.py
src/amuse/community/huayno/readme.txt
src/amuse/community/huayno/src/Makefile
src/amuse/community/huayno/src/common.h
src/amuse/community/huayno/src/evolve.c
src/amuse/community/huayno/src/evolve.h
src/amuse/community/huayno/src/evolve_bs.c
src/amuse/community/huayno/src/evolve_bs.h
src/amuse/community/huayno/src/evolve_cc.c
src/amuse/community/huayno/src/evolve_cc.h
src/amuse/community/huayno/src/evolve_cl.c
src/amuse/community/huayno/src/evolve_cl.h
src/amuse/community/huayno/src/evolve_error_control.c
src/amuse/community/huayno/src/evolve_error_control.h
src/amuse/community/huayno/src/evolve_kepler.c
src/amuse/community/huayno/src/evolve_kepler.h
src/amuse/community/huayno/src/evolve_kern.cl
src/amuse/community/huayno/src/evolve_ok.c
src/amuse/community/huayno/src/evolve_ok.h
src/amuse/community/huayno/src/evolve_sf.c
src/amuse/community/huayno/src/evolve_sf.h
src/amuse/community/huayno/src/evolve_shared.c
src/amuse/community/huayno/src/evolve_shared.h
src/amuse/community/huayno/src/evolve_shared_collisions.c
src/amuse/community/huayno/src/evolve_shared_collisions.h
src/amuse/community/huayno/src/integrators_shared.h
src/amuse/community/huayno/src/simple_hash.c
src/amuse/community/huayno/src/simple_hash.h
src/amuse/community/huayno/src/simple_map.c
src/amuse/community/huayno/src/simple_map.h
src/amuse/community/huayno/src/universal_kepler_solver.h
src/amuse/community/huayno/src/universal_variable_kepler.c
src/amuse/community/huayno/src/universal_variable_kepler.h
support/__init__.py
support/classifiers.py
support/config.py
support/generate_main.py
support/getsp.class
support/getsp.java
support/misc.py
support/setup_codes.py
support/version.py